{
  "advanced-cursors:add-cursor-above": [
    {
      "modifiers": [
        "Alt",
        "Mod"
      ],
      "key": "ArrowUp"
    }
  ],
  "advanced-cursors:add-cursor-below": [
    {
      "modifiers": [
        "Alt",
        "Mod"
      ],
      "key": "ArrowDown"
    }
  ],
  "advanced-cursors:copy-line-down": [
    {
      "modifiers": [
        "Alt",
        "Shift"
      ],
      "key": "ArrowDown"
    }
  ],
  "advanced-cursors:copy-line-up": [
    {
      "modifiers": [
        "Alt",
        "Shift"
      ],
      "key": "ArrowUp"
    }
  ],
  "advanced-cursors:move-to-next-match": [
    {
      "modifiers": [
        "Mod"
      ],
      "key": "D"
    }
  ],
  "insert-template": [
    {
      "modifiers": [
        "Mod"
      ],
      "key": "\\"
    }
  ],
  "editor:toggle-strikethrough": [
    {
      "modifiers": [
        "Mod"
      ],
      "key": "`"
    }
  ],
  "editor:toggle-highlight": [
    {
      "modifiers": [
        "Mod"
      ],
      "key": "J"
    }
  ]
}